LICENSE.txt
MANIFEST.in
README.md
setup.cfg
setup.py
cyvlfeat/__init__.py
cyvlfeat/_static_version.py
cyvlfeat/_version.py
cyvlfeat/cy_util.h
cyvlfeat/cy_util.pxd
cyvlfeat/utils.py
cyvlfeat.egg-info/PKG-INFO
cyvlfeat.egg-info/SOURCES.txt
cyvlfeat.egg-info/dependency_links.txt
cyvlfeat.egg-info/top_level.txt
cyvlfeat/_vl/__init__.py
cyvlfeat/_vl/dsift.pxd
cyvlfeat/_vl/fisher.pxd
cyvlfeat/_vl/generic.pxd
cyvlfeat/_vl/gmm.pxd
cyvlfeat/_vl/hikmeans.pxd
cyvlfeat/_vl/hog.pxd
cyvlfeat/_vl/host.pxd
cyvlfeat/_vl/ikmeans.pxd
cyvlfeat/_vl/kmeans.pxd
cyvlfeat/_vl/mathop.pxd
cyvlfeat/_vl/quickshift.pxd
cyvlfeat/_vl/sift.pxd
cyvlfeat/_vl/vlad.pxd
cyvlfeat/aib/__init__.py
cyvlfeat/data/ascent.descr
cyvlfeat/data/ascent.frame
cyvlfeat/data/hog.mat
cyvlfeat/fisher/__init__.py
cyvlfeat/fisher/cyfisher.c
cyvlfeat/fisher/cyfisher.pyx
cyvlfeat/fisher/fisher.py
cyvlfeat/fisher/tests/__init__.py
cyvlfeat/fisher/tests/fisher_test.py
cyvlfeat/generic/__init__.py
cyvlfeat/generic/generic.c
cyvlfeat/generic/generic.pyx
cyvlfeat/geometry/__init__.py
cyvlfeat/gmm/__init__.py
cyvlfeat/gmm/cygmm.c
cyvlfeat/gmm/cygmm.pyx
cyvlfeat/gmm/gmm.py
cyvlfeat/gmm/tests/__init__.py
cyvlfeat/gmm/tests/test_gmm.py
cyvlfeat/hog/__init__.py
cyvlfeat/hog/cyhog.c
cyvlfeat/hog/cyhog.pyx
cyvlfeat/hog/hog.py
cyvlfeat/hog/tests/__init__.py
cyvlfeat/hog/tests/hog_test.py
cyvlfeat/imop/__init__.py
cyvlfeat/kmeans/__init__.py
cyvlfeat/kmeans/cykmeans.c
cyvlfeat/kmeans/cykmeans.pyx
cyvlfeat/kmeans/hikmeans.py
cyvlfeat/kmeans/ikmeans.py
cyvlfeat/kmeans/kmeans.py
cyvlfeat/kmeans/tests/__init__.py
cyvlfeat/kmeans/tests/kmeans_test.py
cyvlfeat/mser/__init__.py
cyvlfeat/quickshift/__init__.py
cyvlfeat/quickshift/cyquickshift.c
cyvlfeat/quickshift/cyquickshift.pyx
cyvlfeat/quickshift/flatmap.py
cyvlfeat/quickshift/quickshift.py
cyvlfeat/quickshift/tests/__init__.py
cyvlfeat/quickshift/tests/quickshift_test.py
cyvlfeat/sift/__init__.py
cyvlfeat/sift/cysift.c
cyvlfeat/sift/cysift.pyx
cyvlfeat/sift/dsift.py
cyvlfeat/sift/phow.py
cyvlfeat/sift/sift.py
cyvlfeat/sift/tests/__init__.py
cyvlfeat/sift/tests/dsift_test.py
cyvlfeat/sift/tests/phow_test.py
